[
  {
    "lines": {
      "red": [
        [
          [
            775,
            902
          ],
          [
            792,
            935
          ]
        ],
        [
          [
            747,
            917
          ],
          [
            783,
            996
          ]
        ]
      ],
      "green": [
        [
          [
            551,
            1013
          ],
          [
            783,
            1001
          ]
        ],
        [
          [
            554,
            1055
          ],
          [
            790,
            1037
          ]
        ]
      ],
      "blue": [
        [
          [
            828,
            814
          ],
          [
            825,
            1029
          ]
        ],
        [
          [
            792,
            814
          ],
          [
            791,
            1002
          ]
        ]
      ]
    },
    "ellipses": [
      [
        [
          803,
          1000
        ],
        [
          815,
          1001
        ],
        [
          822,
          1017
        ],
        [
          803,
          1031
        ],
        [
          792,
          1014
        ]
      ],
      [
        [
          746,
          892
        ],
        [
          764,
          898
        ],
        [
          758,
          910
        ],
        [
          745,
          909
        ],
        [
          758,
          888
        ]
      ]
    ]
  },
  {
    "lines": {
      "red": [
        [
          [
            755,
            846
          ],
          [
            706,
            908
          ]
        ],
        [
          [
            771,
            865
          ],
          [
            717,
            941
          ]
        ]
      ],
      "green": [
        [
          [
            520,
            886
          ],
          [
            679,
            920
          ]
        ],
        [
          [
            518,
            914
          ],
          [
            664,
            948
          ]
        ]
      ],
      "blue": [
        [
          [
            713,
            782
          ],
          [
            708,
            949
          ]
        ],
        [
          [
            684,
            781
          ],
          [
            681,
            947
          ]
        ]
      ]
    },
    "ellipses": [
      [
        [
          753,
          861
        ],
        [
          749,
          849
        ],
        [
          769,
          852
        ],
        [
          756,
          865
        ],
        [
          774,
          865
        ]
      ],
      [
        [
          683,
          932
        ],
        [
          706,
          921
        ],
        [
          715,
          931
        ],
        [
          694,
          943
        ],
        [
          690,
          917
        ]
      ]
    ]
  },
  {
    "lines": {
      "red": [
        [
          [
            512,
            987
          ],
          [
            730,
            1103
          ]
        ],
        [
          [
            477,
            1000
          ],
          [
            726,
            1138
          ]
        ]
      ],
      "green": [
        [
          [
            636,
            852
          ],
          [
            489,
            952
          ]
        ],
        [
          [
            661,
            860
          ],
          [
            506,
            971
          ]
        ]
      ],
      "blue": [
        [
          [
            491,
            726
          ],
          [
            460,
            983
          ]
        ],
        [
          [
            485,
            981
          ],
          [
            515,
            741
          ]
        ]
      ]
    },
    "ellipses": [
      [
        [
          490,
          1005
        ],
        [
          502,
          1002
        ],
        [
          501,
          984
        ],
        [
          478,
          991
        ],
        [
          490,
          980
        ]
      ],
      [
        [
          619,
          1064
        ],
        [
          642,
          1060
        ],
        [
          635,
          1076
        ],
        [
          619,
          1079
        ],
        [
          631,
          1053
        ]
      ]
    ]
  },
  {
    "lines": {
      "red": [
        [
          [
            224,
            1025
          ],
          [
            458,
            911
          ]
        ],
        [
          [
            254,
            1038
          ],
          [
            467,
            934
          ]
        ]
      ],
      "green": [
        [
          [
            493,
            920
          ],
          [
            613,
            978
          ]
        ],
        [
          [
            484,
            940
          ],
          [
            595,
            1004
          ]
        ]
      ],
      "blue": [
        [
          [
            502,
            737
          ],
          [
            480,
            909
          ]
        ],
        [
          [
            463,
            900
          ],
          [
            476,
            784
          ]
        ]
      ]
    },
    "ellipses": [
      [
        [
          349,
          974
        ],
        [
          330,
          984
        ],
        [
          336,
          967
        ],
        [
          353,
          992
        ],
        [
          334,
          994
        ]
      ],
      [
        [
          456,
          937
        ],
        [
          451,
          921
        ],
        [
          463,
          918
        ],
        [
          467,
          922
        ],
        [
          452,
          929
        ]
      ]
    ]
  }
]